monitoring2/__init__.py
monitoring2-1.3.8.dist-info/LICENSE.txt
monitoring2-1.3.8.dist-info/METADATA
monitoring2-1.3.8.dist-info/WHEEL
monitoring2-1.3.8.dist-info/top_level.txt
monitoring2-1.3.8.dist-info/RECORD
