Metadata-Version: 2.1
Name: monitoring2
Version: 1.3.8
Summary: Библиотека для работы с системой мониторинг 2.0
Home-page: https://pypi.org/manage/project/monitoring2/release/
Author: Dmitry Dimonoff
Author-email: mr.dimonoff@gmail.com
License: UNKNOWN
Platform: UNKNOWN
Classifier: Programming Language :: Python :: 3
Classifier: License :: OSI Approved :: MIT License
Classifier: Operating System :: OS Independent
